LICENSE
MANIFEST.in
README.md
setup.py
django_model_validators.egg-info/PKG-INFO
django_model_validators.egg-info/SOURCES.txt
django_model_validators.egg-info/dependency_links.txt
django_model_validators.egg-info/requires.txt
django_model_validators.egg-info/top_level.txt
model_validators/__init__.py
model_validators/validators.py