Metadata-Version: 1.0
Name: django-model-validators
Version: 0.1a2
Summary: Validators for Django models.
Home-page: https://bitbucket.org/nextscreenlabs/django-model-validators
Author: Jason Christa
Author-email: jason@zeitcode.com
License: UNKNOWN
Platform: UNKNOWN
Classifier: Environment :: Web Environment
Classifier: License :: OSI Approved :: BSD License
Classifier: Framework :: Django
Classifier: Programming Language :: Python
